Metadata-Version: 2.1
Name: quick-styles
Version: 1.0.2
Summary: A ridiculously lightweight Python library for effortlessly applying ANSI escape color & style codes to Windows CMD.
Home-page: https://github.com/imjamnotjelly/quick_styles
Author: imjamnotjelly
License: MIT
Classifier: License :: OSI Approved :: MIT License
Classifier: Topic :: Terminals
Classifier: Operating System :: Microsoft :: Windows
Classifier: Operating System :: OS Independent
License-File: LICENSE.md
